{"hash":"2c4d28672e611272c9d90e4e7a1cab0f70d5b23b","data":{"category":{"id":"psihoterapijski-koncepti","title":"Psihoterapijski koncepti","desc":"Objašnjenja osnovnih teorijskih pojmova iz psihoterapijske prakse koji vam mogu biti korisni u životu.","metaTitle":"Psihoterapijski koncepti | Ubuntu Blog","metaDesc":"Objašnjenja osnovnih teorijskih pojmova iz psihoterapijske prakse koji vam mogu biti korisni u životu.","belongsTo":{"totalCount":0,"pageInfo":{"totalPages":1,"currentPage":1},"edges":[]}}},"context":{}}